{
  "clientes": [
    {
      "id": "dfafs",
      "nome": "Thiago Xavier",
      "telefone": "123456789"
    },
    {
      "id": "ddsaf",
      "nome": "Deborah Aarão",
      "telefone": "3245678"
    },
    {
      "id": "xxuizc",
      "nome": "aaaaaaa",
      "telefone": "22222222"
    },
    {
      "id": "hWoz68",
      "nome": "cad",
      "telefone": "1234"
    }
  ],
  "categorias": [
    {
      "id": "PRNT5G",
      "nome": "a",
      "descricao": "a",
      "ativa": true
    },
    {
      "id": "nJxUpP",
      "nome": "a",
      "descricao": "a",
      "ativa": false
    },
    {
      "id": "dMB8JK",
      "nome": "a",
      "descricao": "a",
      "ativa": true
    },
    {
      "id": "mxzw2i",
      "nome": "aa",
      "descricao": "aa",
      "ativa": false
    },
    {
      "id": "GLTlEx",
      "nome": "aaa",
      "descricao": "aaa",
      "ativa": true
    }
  ]
}